treesimulator/__init__.py
treesimulator/assess_R.py
treesimulator/calc_params.py
treesimulator/generator.py
treesimulator/main.py
treesimulator/mtbd_models.py
treesimulator/sequence_generator.py
treesimulator/simulate_forest.py
treesimulator/simulate_forest_bd.py
treesimulator/simulate_forest_bdei.py
treesimulator/simulate_forest_bdeiss.py
treesimulator/simulate_forest_bdss.py
treesimulator-0.2.27.dist-info/LICENSE
treesimulator-0.2.27.dist-info/METADATA
treesimulator-0.2.27.dist-info/WHEEL
treesimulator-0.2.27.dist-info/entry_points.txt
treesimulator-0.2.27.dist-info/top_level.txt
treesimulator-0.2.27.dist-info/RECORD
