Metadata-Version: 2.1
Name: treesimulator
Version: 0.2.27
Summary: Simulation of rooted phylogenetic trees under a given Multi-Type Birth–Death model, with or without Contact Tracing, with or without a Skyline.
Home-page: https://github.com/evolbioinfo/treesimulator
Author: Anna Zhukova
Author-email: anna.zhukova@pasteur.fr
Keywords: phylogenetics,tree generator,multitype birth-death model,contact tracing,skyline,MTBD,MTBD-CT,MTBD-SKY,MTBD-CT-SKY
Classifier: Development Status :: 4 - Beta
Classifier: Environment :: Console
Classifier: Intended Audience :: Developers
Classifier: Topic :: Scientific/Engineering :: Bio-Informatics
Classifier: Topic :: Software Development
Classifier: Topic :: Software Development :: Libraries :: Python Modules
Requires: six
Requires: ete3
Requires: numpy
Requires: scipy
Requires: sympy
Requires: lifelines
License-File: LICENSE
Requires-Dist: six
Requires-Dist: ete3
Requires-Dist: numpy
Requires-Dist: scipy
Requires-Dist: sympy
Requires-Dist: lifelines
